jimmy_pkg/__init__.py
jimmy_pkg/utils.py
jimmy_pkg-0.1.0.dist-info/METADATA
jimmy_pkg-0.1.0.dist-info/WHEEL
jimmy_pkg-0.1.0.dist-info/top_level.txt
jimmy_pkg-0.1.0.dist-info/RECORD
