Metadata-Version: 2.4
Name: jimmy_pkg
Version: 0.1.0
Summary: Add your description here
Requires-Python: >=3.12
Requires-Dist: jimmy-utils>=1.0.1
